imagedataextractor/__init__.py
imagedataextractor/data.py
imagedataextractor/extract.py
imagedataextractor/figsplit.py
imagedataextractor/utils.py
imagedataextractor/analysis/__init__.py
imagedataextractor/analysis/filtering.py
imagedataextractor/analysis/particlesize.py
imagedataextractor/analysis/shapedetect.py
imagedataextractor/analysis/shapes/__init__.py
imagedataextractor/analysis/shapes/circle.png
imagedataextractor/analysis/shapes/diamond.png
imagedataextractor/analysis/shapes/ellipse.png
imagedataextractor/analysis/shapes/hexagon.png
imagedataextractor/analysis/shapes/rectangle.png
imagedataextractor/analysis/shapes/rod.png
imagedataextractor/analysis/shapes/square.png
imagedataextractor/analysis/shapes/triangle.png
imagedataextractor/models/__init__.py
imagedataextractor/models/frozen_east_text_detection.pb
imagedataextractor/models/seg-model.pt
imagedataextractor/scalebar/__init__.py
imagedataextractor/scalebar/ocr.py
imagedataextractor/scalebar/scalebar.py
imagedataextractor/scalebar/textdetection.py
imagedataextractor/scalebar/utils.py
imagedataextractor/segment/__init__.py
imagedataextractor/segment/cluster.py
imagedataextractor/segment/model.py
imagedataextractor/segment/nnmodules.py
imagedataextractor/segment/uncertainty.py
tests/__init__.py
tests/test_extraction.py
tests/test_scalebar_detection.py
imagedataextractor-2.0.4.dist-info/LICENSE
imagedataextractor-2.0.4.dist-info/METADATA
imagedataextractor-2.0.4.dist-info/WHEEL
imagedataextractor-2.0.4.dist-info/top_level.txt
imagedataextractor-2.0.4.dist-info/RECORD
