Metadata-Version: 2.1
Name: imagedataextractor
Version: 2.0.4
Summary: imagedataextractor is a Python library for electron microscopy image quantification.
Home-page: https://github.com/by256/imagedataextractor
Author: Batuhan Yildirim
Author-email: by256@cam.ac.uk
License: MIT
Platform: UNKNOWN
Classifier: Programming Language :: Python :: 3
Classifier: License :: OSI Approved :: MIT License
Classifier: Operating System :: OS Independent
Requires-Dist: numpy (>=1.19)
Requires-Dist: matplotlib (==2.2.4)
Requires-Dist: torch
Requires-Dist: opencv-python (>=4.2.0.32)
Requires-Dist: pytesseract (==0.3.3)
Requires-Dist: rdfpy (>=1.0.0)
Requires-Dist: pandas
Requires-Dist: chemdataextractor
Requires-Dist: scikit-image
